README.md
setup.cfg
setup.py
cloc/__init__.py
cloc/core.py
cloc/decorators.py
cloc/mixins.py
cloc/types.py
cloc/utils.py
cloc/viewsets.py
cloc.egg-info/PKG-INFO
cloc.egg-info/SOURCES.txt
cloc.egg-info/dependency_links.txt
cloc.egg-info/requires.txt
cloc.egg-info/top_level.txt