Metadata-Version: 2.1
Name: cloc
Version: 0.1.2
Summary: Command Line Object Chaining (cloc) - Modern cli framework for simple and complex cli applications
Home-page: https://www.github.com/tannerburns/cloc
Author: Tanner Burns
Author-email: tjburns102@gmail.com
License: UNKNOWN
Platform: UNKNOWN
Classifier: Operating System :: OS Independent
Classifier: Programming Language :: Python :: 3.7
